zbx_utils/__init__.py
zbx_utils/zbxtags.py
zbx_utils/zbxtpls.py
zbx_utils-1.0.0.dist-info/METADATA
zbx_utils-1.0.0.dist-info/WHEEL
zbx_utils-1.0.0.dist-info/top_level.txt
zbx_utils-1.0.0.dist-info/RECORD
