Metadata-Version: 2.1
Name: zbx_utils
Version: 1.0.0
Summary: Zabbix 辅助与通用功能操作库。
Home-page: https://github.com/gary714/zbx-utils
Author: gary
Author-email: mepmb@sina.com
License: MIT
Project-URL: Homepage, https://github.com/gary714/zbx-utils
Project-URL: Documentation, https://github.com/gary714/zbx-utils
Project-URL: Source, https://github.com/gary714/zbx-utils
Keywords: Zabbix,Utilities
Platform: Linux
Platform: Windows
Classifier: License :: OSI Approved :: MIT License
Classifier: Programming Language :: Python :: 3.6
Classifier: Programming Language :: Python :: 3.7
Classifier: Programming Language :: Python :: 3.8
Classifier: Programming Language :: Python :: 3.9
Requires-Dist: zabbix-api>=0.5.4
